lit_ecology_classifier/__init__.py
lit_ecology_classifier/main.py
lit_ecology_classifier/predict.py
lit_ecology_classifier/test.py
lit_ecology_classifier/data/__init__.py
lit_ecology_classifier/data/datamodule.py
lit_ecology_classifier/data/imagedataset.py
lit_ecology_classifier/data/tardataset.py
lit_ecology_classifier/helpers/__init__.py
lit_ecology_classifier/helpers/argparser.py
lit_ecology_classifier/helpers/calc_class_weights.py
lit_ecology_classifier/helpers/helpers.py
lit_ecology_classifier/helpers/predict_hierarchical.py
lit_ecology_classifier/models/__init__.py
lit_ecology_classifier/models/model.py
lit_ecology_classifier/models/setup_model.py
lit_ecology_classifier-2.0.3.dist-info/LICENSE
lit_ecology_classifier-2.0.3.dist-info/METADATA
lit_ecology_classifier-2.0.3.dist-info/WHEEL
lit_ecology_classifier-2.0.3.dist-info/entry_points.txt
lit_ecology_classifier-2.0.3.dist-info/top_level.txt
lit_ecology_classifier-2.0.3.dist-info/RECORD
