Metadata-Version: 2.1
Name: lit_ecology_classifier
Version: 2.0.3
Summary: Image Classifier optimised for ecology use-cases
Home-page: https://github.com/kaechb/lit_ecology_classifier
Author: Benno Kaech
Author-email: your.email@example.com
Classifier: Programming Language :: Python :: 3
Classifier: License :: OSI Approved :: MIT License
Classifier: Operating System :: OS Independent
Requires-Python: >=3.6
License-File: LICENSE
Requires-Dist: torch
Requires-Dist: torchvision
Requires-Dist: torchaudio
Requires-Dist: lightning
Requires-Dist: numpy
Requires-Dist: scipy
Requires-Dist: pandas
Requires-Dist: matplotlib
Requires-Dist: timm
Requires-Dist: safetensors
Requires-Dist: scikit-learn
